{
    "quotes_list": [
        {
            "quote": "The secret of your future is hidden in your daily routine.",
            "source": "Mike Murdock",
            "citation": "BrainyQuote",
            "year": "2016"
        },
        {
            "quote": "With consistency and reps and routine you're going to achieve your goals and get where you want to be.",
            "source": "Mandy Rose",
            "citation": "BrainyQuote",
            "year": "Unknown"
        },
        {
            "quote": "Scheduls are meant to help, not hinder. Create them with your lifestyle in mind",
            "source": "CHRISSY HALTON",
            "citation": "organise MY House",
            "year": "1985"
        },
        {
            "quote": "Every day of our lives, We are on the verge of making those slight changes that would make all the differences",
            "source": "Mignon Mclaughlin",
            "citation": "organise my house",
            "year": "Unknown"
        },
        {
            "quote": "We are what we repeatedly do",
            "source": "Aristotle",
            "citation": "Organise my house",
            "year": "1867-1934"
        },
        {
            "quote": "Wake up and shine",
            "source": "Jordan Peterson",
            "citation": "organise my house",
            "year": "2018"
        }
    ]
}